rtt_sdk/__init__.py
rtt_sdk/__version__.py
rtt_sdk/client.py
rtt_sdk/exceptions.py
rtt_sdk/helpers.py
rtt_sdk/logging.py
rtt_sdk/models.py
rtt_sdk/openapi.py
rtt_sdk/schema.py
rtt_sdk/slingshot.py
rtt_sdk/stream.py
rtt_sdk-0.2.0.dist-info/LICENSE.txt
rtt_sdk-0.2.0.dist-info/METADATA
rtt_sdk-0.2.0.dist-info/WHEEL
rtt_sdk-0.2.0.dist-info/top_level.txt
rtt_sdk-0.2.0.dist-info/RECORD
