Metadata-Version: 2.1
Name: rtt-sdk
Version: 0.2.0
Summary: Scripting SDK for the Red Team Toolkit platform
Home-page: https://netspi.com
Author: Nick Landers, NetSPI
Author-email: rtt.support@netspi.com
License: UNKNOWN
Platform: UNKNOWN
Classifier: Development Status :: 4 - Beta
Classifier: Programming Language :: Python :: 3
Classifier: License :: OSI Approved :: GNU Lesser General Public License v3 (LGPLv3)
Classifier: Operating System :: OS Independent
Requires-Python: >=3.7
Requires-Dist: colorful (~=0.4.4)
Requires-Dist: pefile (~=2021.5.13)
Requires-Dist: requests (~=2.25.1)
Requires-Dist: websockets (~=8.1)
